setup.py
AsanaToGithub.egg-info/PKG-INFO
AsanaToGithub.egg-info/SOURCES.txt
AsanaToGithub.egg-info/dependency_links.txt
AsanaToGithub.egg-info/entry_points.txt
AsanaToGithub.egg-info/requires.txt
AsanaToGithub.egg-info/top_level.txt
asana_to_github/__init__.py
asana_to_github/asana_to_github.py