Metadata-Version: 1.0
Name: AsanaToGithub
Version: 1.0.0
Summary: Simple script to copy items from Asana to Github issues
Home-page: https://github.com/talha131/asana-to-github
Author: Talha Mansoor
Author-email: talha131@gmail.com
License: Apache License, (2.0)
Download-URL: https://github.com/talha131/AsanaToGithub/tarball/master
Keywords: Asana,Github,Github issues,issue tracker
Platform: UNKNOWN
Classifier: Development Status :: 5 - Production/Stable
Classifier: License :: OSI Approved :: Apache Software License
Classifier: Topic :: Internet :: WWW/HTTP
Classifier: Topic :: Software Development :: Bug Tracking
Classifier: Topic :: Utilities
Classifier: Environment :: Console
Classifier: Intended Audience :: Developers
